pyrobale/__init__.py
pyrobale/StateMachine/__init__.py
pyrobale/client/__init__.py
pyrobale/exceptions/__init__.py
pyrobale/exceptions/common.py
pyrobale/filters/__init__.py
pyrobale/objects/__init__.py
pyrobale/objects/animation.py
pyrobale/objects/audio.py
pyrobale/objects/callbackquery.py
pyrobale/objects/chat.py
pyrobale/objects/chatmember.py
pyrobale/objects/chatphoto.py
pyrobale/objects/contact.py
pyrobale/objects/copytextbutton.py
pyrobale/objects/document.py
pyrobale/objects/enums.py
pyrobale/objects/file.py
pyrobale/objects/forwardorigin.py
pyrobale/objects/inlinekeyboardbutton.py
pyrobale/objects/inlinekeyboardmarkup.py
pyrobale/objects/inputfile.py
pyrobale/objects/inputmedias.py
pyrobale/objects/invitelink.py
pyrobale/objects/invoice.py
pyrobale/objects/keyboardbutton.py
pyrobale/objects/labeledprice.py
pyrobale/objects/location.py
pyrobale/objects/message.py
pyrobale/objects/messageid.py
pyrobale/objects/newchatmembers.py
pyrobale/objects/photosize.py
pyrobale/objects/precheckoutquery.py
pyrobale/objects/replykeyboardmarkup.py
pyrobale/objects/sticker.py
pyrobale/objects/stickerset.py
pyrobale/objects/successfulpayment.py
pyrobale/objects/transaction.py
pyrobale/objects/update.py
pyrobale/objects/user.py
pyrobale/objects/utils.py
pyrobale/objects/video.py
pyrobale/objects/voice.py
pyrobale/objects/webappdata.py
pyrobale/objects/webappinfo.py
pyrobale-0.6.8.1.dist-info/METADATA
pyrobale-0.6.8.1.dist-info/WHEEL
pyrobale-0.6.8.1.dist-info/licenses/LICENSE
pyrobale-0.6.8.1.dist-info/RECORD
