Metadata-Version: 2.4
Name: pyrobale
Version: 0.6.8.1
Summary: A python wrapper for bale api
Project-URL: github, https://github.com/pyrobale/pyrobale
Project-URL: website, https://pyrobale.ir
Project-URL: documentation, https://docs.pyrobale.ir
Author-email: Ali Safamanesh <daradege@proton.me>, Aydin Rahbaran <codewizaard9@gmail.com>
License: MIT License
License-File: LICENSE
Classifier: License :: OSI Approved :: MIT License
Classifier: Operating System :: OS Independent
Classifier: Programming Language :: Python :: 3
Requires-Python: >=3.9
Requires-Dist: aiohttp
Requires-Dist: beautifulsoup4
